ucrs/__init__.py
ucrs/py.typed
ucrs-0.2.1.dist-info/LICENSE
ucrs-0.2.1.dist-info/METADATA
ucrs-0.2.1.dist-info/WHEEL
ucrs-0.2.1.dist-info/RECORD
