Metadata-Version: 2.3
Name: ucrs
Version: 0.2.1
Summary: UCRS a single wrapper class that accepts any CRS input and lazily converts to an instance of any library you need (e.g. cartopy, osgeo).
Author: Panos Mavrogiorgos
Author-email: pmav99@gmail.com
Requires-Python: >=3.10
Classifier: Programming Language :: Python :: 3
Classifier: Programming Language :: Python :: 3.10
Classifier: Programming Language :: Python :: 3.11
Classifier: Programming Language :: Python :: 3.12
Classifier: Programming Language :: Python :: 3.13
Provides-Extra: cartopy
Provides-Extra: complete
Provides-Extra: dev
Provides-Extra: gdal
Provides-Extra: test
Requires-Dist: cartopy ; extra == "cartopy"
Requires-Dist: cartopy ; extra == "complete"
Requires-Dist: gdal ; extra == "complete"
Requires-Dist: gdal ; extra == "gdal"
Requires-Dist: ipython ; extra == "dev"
Requires-Dist: pyproj
Requires-Dist: pyright (>=1.1.0) ; extra == "dev"
Requires-Dist: pytest (>=8.0.0) ; extra == "dev"
Requires-Dist: pytest (>=8.0.0) ; extra == "test"
Requires-Dist: pytest-cov (>=4.1.0) ; extra == "dev"
Requires-Dist: pytest-cov (>=4.1.0) ; extra == "test"
Requires-Dist: pytest-xdist (>=3.5.0) ; extra == "dev"
Requires-Dist: pytest-xdist (>=3.5.0) ; extra == "test"
